titulky.py
titulky-1.0.2.dist-info/LICENSE
titulky-1.0.2.dist-info/METADATA
titulky-1.0.2.dist-info/WHEEL
titulky-1.0.2.dist-info/entry_points.txt
titulky-1.0.2.dist-info/top_level.txt
titulky-1.0.2.dist-info/RECORD
