Metadata-Version: 2.1
Name: titulky
Version: 1.0.2
Summary: Tiny SubRip subtitles editor
Home-page: http://pypi.org/project/titulky/
Author: Alexander Theler
License: UNKNOWN
Project-URL: GitHub, https://github.com/atheler/titulky
Project-URL: Bug Tracker, https://github.com/atheler/titulky/issues
Platform: UNKNOWN
Classifier: Development Status :: 3 - Alpha
Classifier: Environment :: Console
Classifier: Environment :: MacOS X
Classifier: Intended Audience :: Developers
Classifier: Intended Audience :: End Users/Desktop
Classifier: Intended Audience :: Other Audience
Classifier: License :: OSI Approved :: GNU General Public License v3 (GPLv3)
Classifier: Natural Language :: English
Classifier: Operating System :: OS Independent
Classifier: Programming Language :: Python :: 3
Classifier: Topic :: Desktop Environment
Classifier: Topic :: Games/Entertainment
Classifier: Topic :: Multimedia
Classifier: Topic :: Terminals
Classifier: Topic :: Text Processing
Classifier: Topic :: Utilities
Requires-Python: >=3.6
